libname/__init__.py
libname/farosat.py
Farosat-0.0.3.dist-info/LICENSE
Farosat-0.0.3.dist-info/METADATA
Farosat-0.0.3.dist-info/WHEEL
Farosat-0.0.3.dist-info/top_level.txt
Farosat-0.0.3.dist-info/RECORD
