Metadata-Version: 2.1
Name: Farosat
Version: 0.0.3
Summary: Just use your Farosat
Home-page: UNKNOWN
Author: Asadbek Mirtazayev
Author-email: <asadbekmirtazayev007@gmail.com>
License: UNKNOWN
Keywords: python,farosat
Platform: UNKNOWN
Classifier: Development Status :: 1 - Planning
Classifier: Intended Audience :: Developers
Classifier: Programming Language :: Python :: 3
Classifier: Operating System :: Unix
Classifier: Operating System :: MacOS :: MacOS X
Classifier: Operating System :: Microsoft :: Windows
